{
  "started_at": "2026-03-01T21:58:51.630945",
  "updated_at": "2026-03-04T17:43:20.040457",
  "completed": [],
  "failed": [
    {
      "processo_id": "006800.000122/2026-12",
      "error": "Message: invalid session id; For documentation on this error, please visit: https://www.selenium.dev/documentation/webdriver/troubleshooting/errors#invalidsessionidexception\nStacktrace:\nSymbols not available. Dumping unresolved backtrace:\n\t0x1227dd3\n\t0x1227e14\n\t0x1031bee\n\t0x106f2d5\n\t0x109e8f6\n\t0x109a491\n\t0x1099ab2\n\t0x100500e\n\t0x10055ae\n\t0x1005a8d\n\t0x1486924\n\t0x1481bf7\n\t0x149f5a0\n\t0x1240f58\n\t0x124891d\n\t0x1004c69\n\t0x10042b0\n\t0x15e876f\n\t0x75f3fcc9\n\t0x774882ae\n\t0x7748827e\n",
      "at": "2026-03-02T11:39:31.405867"
    },
    {
      "processo_id": "006800.000122/2026-12",
      "error": "extraction failed",
      "at": "2026-03-02T11:41:20.123569"
    },
    {
      "processo_id": "006800.000122/2026-12",
      "error": "Message: invalid session id; For documentation on this error, please visit: https://www.selenium.dev/documentation/webdriver/troubleshooting/errors#invalidsessionidexception\nStacktrace:\nSymbols not available. Dumping unresolved backtrace:\n\t0x1227dd3\n\t0x1227e14\n\t0x1031bee\n\t0x106f2d5\n\t0x109e8f6\n\t0x109a491\n\t0x1099ab2\n\t0x100500e\n\t0x10055ae\n\t0x1005a8d\n\t0x1486924\n\t0x1481bf7\n\t0x149f5a0\n\t0x1240f58\n\t0x124891d\n\t0x1004c69\n\t0x10042b0\n\t0x15e876f\n\t0x75f3fcc9\n\t0x774882ae\n\t0x7748827e\n",
      "at": "2026-03-02T11:43:24.627437"
    },
    {
      "processo_id": "FIL-PRO-2023/00482",
      "error": "extraction failed",
      "at": "2026-03-02T12:45:49.891578"
    },
    {
      "processo_id": "006800.000122/2026-12",
      "error": "Message: invalid session id; For documentation on this error, please visit: https://www.selenium.dev/documentation/webdriver/troubleshooting/errors#invalidsessionidexception\nStacktrace:\nSymbols not available. Dumping unresolved backtrace:\n\t0x1227dd3\n\t0x1227e14\n\t0x1031bee\n\t0x106f2d5\n\t0x109e8f6\n\t0x109a491\n\t0x1099ab2\n\t0x100500e\n\t0x10055ae\n\t0x1005a8d\n\t0x1486924\n\t0x1481bf7\n\t0x149f5a0\n\t0x1240f58\n\t0x124891d\n\t0x1004c69\n\t0x10042b0\n\t0x15e876f\n\t0x75f3fcc9\n\t0x774882ae\n\t0x7748827e\n",
      "at": "2026-03-02T18:03:06.037027"
    },
    {
      "processo_id": "006800.000202/2026-60",
      "error": "Message: invalid session id; For documentation on this error, please visit: https://www.selenium.dev/documentation/webdriver/troubleshooting/errors#invalidsessionidexception\nStacktrace:\nSymbols not available. Dumping unresolved backtrace:\n\t0x1227dd3\n\t0x1227e14\n\t0x1031bee\n\t0x106f2d5\n\t0x109e8f6\n\t0x109a491\n\t0x1099ab2\n\t0x100500e\n\t0x10055ae\n\t0x1005a8d\n\t0x1486924\n\t0x1481bf7\n\t0x149f5a0\n\t0x1240f58\n\t0x124891d\n\t0x1004c69\n\t0x10042b0\n\t0x15e876f\n\t0x75f3fcc9\n\t0x774882ae\n\t0x7748827e\n",
      "at": "2026-03-02T18:03:09.047038"
    },
    {
      "processo_id": "001200000021/2025-06",
      "error": "Message: invalid session id; For documentation on this error, please visit: https://www.selenium.dev/documentation/webdriver/troubleshooting/errors#invalidsessionidexception\nStacktrace:\nSymbols not available. Dumping unresolved backtrace:\n\t0x1227dd3\n\t0x1227e14\n\t0x1031bee\n\t0x106f2d5\n\t0x109e8f6\n\t0x109a491\n\t0x1099ab2\n\t0x100500e\n\t0x10055ae\n\t0x1005a8d\n\t0x1486924\n\t0x1481bf7\n\t0x149f5a0\n\t0x1240f58\n\t0x124891d\n\t0x1004c69\n\t0x10042b0\n\t0x15e876f\n\t0x75f3fcc9\n\t0x774882ae\n\t0x7748827e\n",
      "at": "2026-03-02T18:03:12.066744"
    },
    {
      "processo_id": "006800.000136/2026-28",
      "error": "Message: invalid session id; For documentation on this error, please visit: https://www.selenium.dev/documentation/webdriver/troubleshooting/errors#invalidsessionidexception\nStacktrace:\nSymbols not available. Dumping unresolved backtrace:\n\t0x1227dd3\n\t0x1227e14\n\t0x1031bee\n\t0x106f2d5\n\t0x109e8f6\n\t0x109a491\n\t0x1099ab2\n\t0x100500e\n\t0x10055ae\n\t0x1005a8d\n\t0x1486924\n\t0x1481bf7\n\t0x149f5a0\n\t0x1240f58\n\t0x124891d\n\t0x1004c69\n\t0x10042b0\n\t0x15e876f\n\t0x75f3fcc9\n\t0x774882ae\n\t0x7748827e\n",
      "at": "2026-03-02T18:03:15.072473"
    },
    {
      "processo_id": "006800.000105/2026-77",
      "error": "Message: invalid session id; For documentation on this error, please visit: https://www.selenium.dev/documentation/webdriver/troubleshooting/errors#invalidsessionidexception\nStacktrace:\nSymbols not available. Dumping unresolved backtrace:\n\t0x1227dd3\n\t0x1227e14\n\t0x1031bee\n\t0x106f2d5\n\t0x109e8f6\n\t0x109a491\n\t0x1099ab2\n\t0x100500e\n\t0x10055ae\n\t0x1005a8d\n\t0x1486924\n\t0x1481bf7\n\t0x149f5a0\n\t0x1240f58\n\t0x124891d\n\t0x1004c69\n\t0x10042b0\n\t0x15e876f\n\t0x75f3fcc9\n\t0x774882ae\n\t0x7748827e\n",
      "at": "2026-03-02T18:03:18.085126"
    },
    {
      "processo_id": "006800.000354/2026-62",
      "error": "Message: invalid session id; For documentation on this error, please visit: https://www.selenium.dev/documentation/webdriver/troubleshooting/errors#invalidsessionidexception\nStacktrace:\nSymbols not available. Dumping unresolved backtrace:\n\t0x1227dd3\n\t0x1227e14\n\t0x1031bee\n\t0x106f2d5\n\t0x109e8f6\n\t0x109a491\n\t0x1099ab2\n\t0x100500e\n\t0x10055ae\n\t0x1005a8d\n\t0x1486924\n\t0x1481bf7\n\t0x149f5a0\n\t0x1240f58\n\t0x124891d\n\t0x1004c69\n\t0x10042b0\n\t0x15e876f\n\t0x75f3fcc9\n\t0x774882ae\n\t0x7748827e\n",
      "at": "2026-03-02T18:03:21.099178"
    },
    {
      "processo_id": "006800.000350/2026-84",
      "error": "Message: invalid session id; For documentation on this error, please visit: https://www.selenium.dev/documentation/webdriver/troubleshooting/errors#invalidsessionidexception\nStacktrace:\nSymbols not available. Dumping unresolved backtrace:\n\t0x1227dd3\n\t0x1227e14\n\t0x1031bee\n\t0x106f2d5\n\t0x109e8f6\n\t0x109a491\n\t0x1099ab2\n\t0x100500e\n\t0x10055ae\n\t0x1005a8d\n\t0x1486924\n\t0x1481bf7\n\t0x149f5a0\n\t0x1240f58\n\t0x124891d\n\t0x1004c69\n\t0x10042b0\n\t0x15e876f\n\t0x75f3fcc9\n\t0x774882ae\n\t0x7748827e\n",
      "at": "2026-03-02T18:03:24.107642"
    },
    {
      "processo_id": "006800.000053/2026-39",
      "error": "Message: invalid session id; For documentation on this error, please visit: https://www.selenium.dev/documentation/webdriver/troubleshooting/errors#invalidsessionidexception\nStacktrace:\nSymbols not available. Dumping unresolved backtrace:\n\t0x1227dd3\n\t0x1227e14\n\t0x1031bee\n\t0x106f2d5\n\t0x109e8f6\n\t0x109a491\n\t0x1099ab2\n\t0x100500e\n\t0x10055ae\n\t0x1005a8d\n\t0x1486924\n\t0x1481bf7\n\t0x149f5a0\n\t0x1240f58\n\t0x124891d\n\t0x1004c69\n\t0x10042b0\n\t0x15e876f\n\t0x75f3fcc9\n\t0x774882ae\n\t0x7748827e\n",
      "at": "2026-03-02T18:03:27.120759"
    },
    {
      "processo_id": "CET-PRO-2025/01028",
      "error": "Message: invalid session id; For documentation on this error, please visit: https://www.selenium.dev/documentation/webdriver/troubleshooting/errors#invalidsessionidexception\nStacktrace:\nSymbols not available. Dumping unresolved backtrace:\n\t0x1227dd3\n\t0x1227e14\n\t0x1031bee\n\t0x106f2d5\n\t0x109e8f6\n\t0x109a491\n\t0x1099ab2\n\t0x100500e\n\t0x10055ae\n\t0x1005a8d\n\t0x1486924\n\t0x1481bf7\n\t0x149f5a0\n\t0x1240f58\n\t0x124891d\n\t0x1004c69\n\t0x10042b0\n\t0x15e876f\n\t0x75f3fcc9\n\t0x774882ae\n\t0x7748827e\n",
      "at": "2026-03-02T18:03:30.130217"
    },
    {
      "processo_id": "006800.000122/2026-12",
      "error": "extraction failed",
      "at": "2026-03-02T18:04:47.913799"
    },
    {
      "processo_id": "006800.000202/2026-60",
      "error": "extraction failed",
      "at": "2026-03-02T18:05:58.381892"
    },
    {
      "processo_id": "006800.000354/2026-62",
      "error": "extraction failed",
      "at": "2026-03-02T19:35:15.872419"
    },
    {
      "processo_id": "006800.000350/2026-84",
      "error": "extraction failed",
      "at": "2026-03-02T19:35:57.066154"
    },
    {
      "processo_id": "000700.000845/2026-55",
      "error": "extraction failed",
      "at": "2026-03-02T20:14:34.636861"
    },
    {
      "processo_id": "000184.000478/2026-76",
      "error": "extraction failed",
      "at": "2026-03-02T20:40:00.699736"
    },
    {
      "processo_id": "TUR-PRO-2025/01221",
      "error": "extraction failed",
      "at": "2026-03-02T22:44:43.794244"
    },
    {
      "processo_id": "TUR-PRO-2025/01221",
      "error": "Message: invalid session id; For documentation on this error, please visit: https://www.selenium.dev/documentation/webdriver/troubleshooting/errors#invalidsessionidexception\nStacktrace:\nSymbols not available. Dumping unresolved backtrace:\n\t0x1227dd3\n\t0x1227e14\n\t0x1031bee\n\t0x106f2d5\n\t0x109e8f6\n\t0x109a491\n\t0x1099ab2\n\t0x100500e\n\t0x10055ae\n\t0x1005a8d\n\t0x1486924\n\t0x1481bf7\n\t0x149f5a0\n\t0x1240f58\n\t0x124891d\n\t0x1004c69\n\t0x10042b0\n\t0x15e876f\n\t0x75f3fcc9\n\t0x774882ae\n\t0x7748827e\n",
      "at": "2026-03-03T08:04:38.529940"
    },
    {
      "processo_id": "006800.000331/2026-58",
      "error": "Message: invalid session id; For documentation on this error, please visit: https://www.selenium.dev/documentation/webdriver/troubleshooting/errors#invalidsessionidexception\nStacktrace:\nSymbols not available. Dumping unresolved backtrace:\n\t0x1227dd3\n\t0x1227e14\n\t0x1031bee\n\t0x106f2d5\n\t0x109e8f6\n\t0x109a491\n\t0x1099ab2\n\t0x100500e\n\t0x10055ae\n\t0x1005a8d\n\t0x1486924\n\t0x1481bf7\n\t0x149f5a0\n\t0x1240f58\n\t0x124891d\n\t0x1004c69\n\t0x10042b0\n\t0x15e876f\n\t0x75f3fcc9\n\t0x774882ae\n\t0x7748827e\n",
      "at": "2026-03-03T08:04:41.619435"
    },
    {
      "processo_id": "TUR-PRO-2025/01221",
      "error": "Message: invalid session id; For documentation on this error, please visit: https://www.selenium.dev/documentation/webdriver/troubleshooting/errors#invalidsessionidexception\nStacktrace:\nSymbols not available. Dumping unresolved backtrace:\n\t0x1227dd3\n\t0x1227e14\n\t0x1031bee\n\t0x106f2d5\n\t0x109e8f6\n\t0x109a491\n\t0x1099ab2\n\t0x100500e\n\t0x10055ae\n\t0x1005a8d\n\t0x1486924\n\t0x1481bf7\n\t0x149f5a0\n\t0x1240f58\n\t0x124891d\n\t0x1004c69\n\t0x10042b0\n\t0x15e876f\n\t0x75f3fcc9\n\t0x774882ae\n\t0x7748827e\n",
      "at": "2026-03-03T08:04:44.632763"
    },
    {
      "processo_id": "TUR-PRO-2025/01221",
      "error": "Message: invalid session id; For documentation on this error, please visit: https://www.selenium.dev/documentation/webdriver/troubleshooting/errors#invalidsessionidexception\nStacktrace:\nSymbols not available. Dumping unresolved backtrace:\n\t0x1227dd3\n\t0x1227e14\n\t0x1031bee\n\t0x106f2d5\n\t0x109e8f6\n\t0x109a491\n\t0x1099ab2\n\t0x100500e\n\t0x10055ae\n\t0x1005a8d\n\t0x1486924\n\t0x1481bf7\n\t0x149f5a0\n\t0x1240f58\n\t0x124891d\n\t0x1004c69\n\t0x10042b0\n\t0x15e876f\n\t0x75f3fcc9\n\t0x774882ae\n\t0x7748827e\n",
      "at": "2026-03-03T08:04:47.651009"
    },
    {
      "processo_id": "006800.000285/2026-97",
      "error": "Message: invalid session id; For documentation on this error, please visit: https://www.selenium.dev/documentation/webdriver/troubleshooting/errors#invalidsessionidexception\nStacktrace:\nSymbols not available. Dumping unresolved backtrace:\n\t0x1227dd3\n\t0x1227e14\n\t0x1031bee\n\t0x106f2d5\n\t0x109e8f6\n\t0x109a491\n\t0x1099ab2\n\t0x100500e\n\t0x10055ae\n\t0x1005a8d\n\t0x1486924\n\t0x1481bf7\n\t0x149f5a0\n\t0x1240f58\n\t0x124891d\n\t0x1004c69\n\t0x10042b0\n\t0x15e876f\n\t0x75f3fcc9\n\t0x774882ae\n\t0x7748827e\n",
      "at": "2026-03-03T08:04:50.665047"
    },
    {
      "processo_id": "006800.000329/2026-89",
      "error": "Message: invalid session id; For documentation on this error, please visit: https://www.selenium.dev/documentation/webdriver/troubleshooting/errors#invalidsessionidexception\nStacktrace:\nSymbols not available. Dumping unresolved backtrace:\n\t0x1227dd3\n\t0x1227e14\n\t0x1031bee\n\t0x106f2d5\n\t0x109e8f6\n\t0x109a491\n\t0x1099ab2\n\t0x100500e\n\t0x10055ae\n\t0x1005a8d\n\t0x1486924\n\t0x1481bf7\n\t0x149f5a0\n\t0x1240f58\n\t0x124891d\n\t0x1004c69\n\t0x10042b0\n\t0x15e876f\n\t0x75f3fcc9\n\t0x774882ae\n\t0x7748827e\n",
      "at": "2026-03-03T08:04:53.679114"
    },
    {
      "processo_id": "006800.000185/2026-61",
      "error": "Message: invalid session id; For documentation on this error, please visit: https://www.selenium.dev/documentation/webdriver/troubleshooting/errors#invalidsessionidexception\nStacktrace:\nSymbols not available. Dumping unresolved backtrace:\n\t0x1227dd3\n\t0x1227e14\n\t0x1031bee\n\t0x106f2d5\n\t0x109e8f6\n\t0x109a491\n\t0x1099ab2\n\t0x100500e\n\t0x10055ae\n\t0x1005a8d\n\t0x1486924\n\t0x1481bf7\n\t0x149f5a0\n\t0x1240f58\n\t0x124891d\n\t0x1004c69\n\t0x10042b0\n\t0x15e876f\n\t0x75f3fcc9\n\t0x774882ae\n\t0x7748827e\n",
      "at": "2026-03-03T08:04:56.697289"
    },
    {
      "processo_id": "006800.000328/2026-34",
      "error": "Message: invalid session id; For documentation on this error, please visit: https://www.selenium.dev/documentation/webdriver/troubleshooting/errors#invalidsessionidexception\nStacktrace:\nSymbols not available. Dumping unresolved backtrace:\n\t0x1227dd3\n\t0x1227e14\n\t0x1031bee\n\t0x106f2d5\n\t0x109e8f6\n\t0x109a491\n\t0x1099ab2\n\t0x100500e\n\t0x10055ae\n\t0x1005a8d\n\t0x1486924\n\t0x1481bf7\n\t0x149f5a0\n\t0x1240f58\n\t0x124891d\n\t0x1004c69\n\t0x10042b0\n\t0x15e876f\n\t0x75f3fcc9\n\t0x774882ae\n\t0x7748827e\n",
      "at": "2026-03-03T08:04:59.712574"
    },
    {
      "processo_id": "006800.000200/2026-71",
      "error": "Message: invalid session id; For documentation on this error, please visit: https://www.selenium.dev/documentation/webdriver/troubleshooting/errors#invalidsessionidexception\nStacktrace:\nSymbols not available. Dumping unresolved backtrace:\n\t0x1227dd3\n\t0x1227e14\n\t0x1031bee\n\t0x106f2d5\n\t0x109e8f6\n\t0x109a491\n\t0x1099ab2\n\t0x100500e\n\t0x10055ae\n\t0x1005a8d\n\t0x1486924\n\t0x1481bf7\n\t0x149f5a0\n\t0x1240f58\n\t0x124891d\n\t0x1004c69\n\t0x10042b0\n\t0x15e876f\n\t0x75f3fcc9\n\t0x774882ae\n\t0x7748827e\n",
      "at": "2026-03-03T08:05:02.727486"
    },
    {
      "processo_id": "006800.000122/2026-12",
      "error": "extraction failed",
      "at": "2026-03-03T13:18:07.257672"
    },
    {
      "processo_id": "006800.000202/2026-60",
      "error": "extraction failed",
      "at": "2026-03-03T13:19:43.686852"
    },
    {
      "processo_id": "001200000021/2025-06",
      "error": "Message: invalid session id: session deleted as the browser has closed the connection\nfrom disconnected: not connected to DevTools\n  (Session info: chrome=145.0.7632.117); For documentation on this error, please visit: https://www.selenium.dev/documentation/webdriver/troubleshooting/errors#invalidsessionidexception\nStacktrace:\nSymbols not available. Dumping unresolved backtrace:\n\t0xb97dd3\n\t0xb97e14\n\t0x9a1db0\n\t0x990d4e\n\t0x9af895\n\t0xa152ec\n\t0xa2b0d9\n\t0xa0e7d6\n\t0x9e0049\n\t0x9e0e04\n\t0xdf6924\n\t0xdf1bf7\n\t0xe0f5a0\n\t0xbb0f58\n\t0xbb891d\n\t0xba0648\n\t0xba0812\n\t0xb8a21a\n\t0x76f5fcc9\n\t0x778f82ae\n\t0x778f827e\n",
      "at": "2026-03-03T13:20:24.190970"
    },
    {
      "processo_id": "006800.000202/2026-60",
      "error": "Message: no such window: target window already closed\nfrom unknown error: web view not found\n  (Session info: chrome=145.0.7632.117)\nStacktrace:\nSymbols not available. Dumping unresolved backtrace:\n\t0xb97dd3\n\t0xb97e14\n\t0x9a1db0\n\t0x9808d3\n\t0xa150fb\n\t0xa2b0d9\n\t0xa0e7d6\n\t0x9e0049\n\t0x9e0e04\n\t0xdf6924\n\t0xdf1bf7\n\t0xe0f5a0\n\t0xbb0f58\n\t0xbb891d\n\t0xba0648\n\t0xba0812\n\t0xb8a21a\n\t0x76f5fcc9\n\t0x778f82ae\n\t0x778f827e\n",
      "at": "2026-03-03T14:26:55.768692"
    },
    {
      "processo_id": "TUR-PRO-2025/01221",
      "error": "extraction failed",
      "at": "2026-03-04T16:53:18.473421"
    },
    {
      "processo_id": "006800.000185/2026-61",
      "error": "extraction failed",
      "at": "2026-03-04T17:37:43.761223"
    }
  ],
  "pending": [
    "006800.000122/2026-12",
    "006800.000202/2026-60",
    "001200000021/2025-06",
    "006800.000136/2026-28",
    "006800.000105/2026-77",
    "006800.000354/2026-62",
    "006800.000350/2026-84",
    "006800.000053/2026-39",
    "CET-PRO-2025/01028",
    "TUR-PRO-2025/01221",
    "006800.000327/2026-90",
    "006800.000096/2026-14",
    "006800.000197/2026-95",
    "TUR-PRO-2025/01233",
    "TUR-PRO-2025/01221",
    "TUR-PRO-2025/01221",
    "006800.000295/2026-22",
    "006800.000124/2026-01",
    "000700.000845/2026-55",
    "TUR-PRO-2025/01221",
    "006800.000343/2026-82",
    "TUR-PRO-2025/01221",
    "006800.000294/2026-88",
    "TUR-PRO-2025/01234",
    "TUR-PRO-2025/01221",
    "000184.000478/2026-76",
    "TUR-PRO-2025/01229",
    "TUR-PRO-2025/01230",
    "006800.000045/2026-92",
    "006800.000209/2026-81",
    "006800.000338/2026-70",
    "006800.000161/2026-10",
    "006800.000187/2026-50",
    "000184.000502/2026-77",
    "006800.000311/2026-87",
    "006800.000180/2026-38",
    "006800.000199/2026-84",
    "006800.000312/2026-21",
    "006800.000184/2026-16",
    "006800.000325/2026-09",
    "006800.000270/2026-29",
    "006800.000305/2026-20",
    "006800.000274/2026-15",
    "TUR-PRO-2025/01221",
    "006800.000276/2026-04",
    "TUR-PRO-2025/01256",
    "CET-PRO-2025/02888",
    "006800.000323/2026-10",
    "006800.000152/2026-11",
    "TUR-PRO-2025/01221",
    "TUR-PRO-2025/01221",
    "006800.000106/2026-11",
    "006800.000211/2026-51",
    "TUR-PRO-2025/01233",
    "TUR-PRO-2025/01221",
    "TUR-PRO-2025/01235",
    "006800.000310/2026-32",
    "006800.000178/2026-69",
    "TUR-PRO-2025/01222",
    "006800.000273/2026-62",
    "006800.000307/2026-19",
    "006800.000227/2026-63",
    "TUR-PRO-2025/01215",
    "TUR-PRO-2025/01219",
    "TUR-PRO-2025/01221",
    "006800.000334/2026-91",
    "006800.000271/2026-73",
    "TUR-PRO-2025/01221",
    "TUR-PRO-2025/01221",
    "TUR-PRO-2025/01221",
    "TUR-PRO-2025/01225",
    "006800.000177/2026-14",
    "TUR-PRO-2025/01256",
    "006800.000213/2026-40",
    "TRA-PRO-2025/00286",
    "000184.000037/2026-74",
    "TUR-PRO-2025/01221",
    "TUR-PRO-2025/01233",
    "TUR-PRO-2025/01221",
    "SME-PRO-2025/61739",
    "12/500.078/2021",
    "006800.000326/2026-45",
    "000184.000137/2026-09",
    "TUR-PRO-2025/01221",
    "006800.000127/2026-37",
    "TUR-PRO-2025/01221",
    "TUR-PRO-2025/01232",
    "TUR-PRO-2025/01218",
    "006800.000202/2026-60",
    "006800.000324/2026-56",
    "006800.000164/2026-45",
    "000184.000082/2026-29",
    "006800.000257/2026-70",
    "006800.000272/2026-18",
    "006800.000335/2026-36",
    "006300.000004/2026-37",
    "006800.000330/2026-11",
    "006800.000309/2026-16",
    "006800.000055/2026-28",
    "006800.000306/2026-74",
    "000700.000325/2025-61",
    "TUR-PRO-2025/01221",
    "006800.000331/2026-58",
    "TUR-PRO-2025/01221",
    "TUR-PRO-2025/01221",
    "006800.000285/2026-97",
    "006800.000329/2026-89",
    "006800.000185/2026-61",
    "006800.000328/2026-34",
    "006800.000200/2026-71",
    "TUR-PRO-2025/01221",
    "TUR-PRO-2025/01256",
    "006800.000097/2026-69",
    "006800.000269/2026-02",
    "001200.000596/2026-00",
    "001200.000602/2026-11"
  ],
  "stats": {
    "total": 117,
    "success": 0,
    "failed": 35,
    "skipped": 0,
    "no_document": 237
  },
  "no_document": [
    {
      "processo_id": "006800.000122/2026-12",
      "at": "2026-03-02T19:30:29.321312"
    },
    {
      "processo_id": "006800.000202/2026-60",
      "at": "2026-03-02T19:31:27.036284"
    },
    {
      "processo_id": "001200000021/2025-06",
      "at": "2026-03-02T19:32:36.537599"
    },
    {
      "processo_id": "006800.000136/2026-28",
      "at": "2026-03-02T19:33:26.962722"
    },
    {
      "processo_id": "006800.000105/2026-77",
      "at": "2026-03-02T19:34:35.574520"
    },
    {
      "processo_id": "006800.000053/2026-39",
      "at": "2026-03-02T19:37:28.085611"
    },
    {
      "processo_id": "CET-PRO-2025/01028",
      "at": "2026-03-02T19:38:48.437193"
    },
    {
      "processo_id": "TUR-PRO-2025/01221",
      "at": "2026-03-02T19:40:01.502127"
    },
    {
      "processo_id": "006800.000327/2026-90",
      "at": "2026-03-02T19:41:17.949044"
    },
    {
      "processo_id": "006800.000096/2026-14",
      "at": "2026-03-02T19:43:30.501512"
    },
    {
      "processo_id": "006800.000197/2026-95",
      "at": "2026-03-02T19:45:55.149513"
    },
    {
      "processo_id": "TUR-PRO-2025/01233",
      "at": "2026-03-02T19:47:01.685837"
    },
    {
      "processo_id": "006800.000295/2026-22",
      "at": "2026-03-02T19:54:10.807402"
    },
    {
      "processo_id": "006800.000124/2026-01",
      "at": "2026-03-02T19:58:03.813443"
    },
    {
      "processo_id": "006800.000343/2026-82",
      "at": "2026-03-02T20:18:27.815683"
    },
    {
      "processo_id": "006800.000294/2026-88",
      "at": "2026-03-02T20:21:51.899982"
    },
    {
      "processo_id": "TUR-PRO-2025/01234",
      "at": "2026-03-02T20:23:42.193772"
    },
    {
      "processo_id": "006800.000354/2026-62",
      "at": "2026-03-02T20:56:31.722442"
    },
    {
      "processo_id": "006800.000350/2026-84",
      "at": "2026-03-02T20:57:26.745555"
    },
    {
      "processo_id": "000700.000845/2026-55",
      "at": "2026-03-02T21:26:37.373144"
    },
    {
      "processo_id": "000184.000478/2026-76",
      "at": "2026-03-02T22:17:23.966917"
    },
    {
      "processo_id": "TUR-PRO-2025/01229",
      "at": "2026-03-02T22:19:05.274951"
    },
    {
      "processo_id": "TUR-PRO-2025/01230",
      "at": "2026-03-02T22:20:48.916842"
    },
    {
      "processo_id": "006800.000045/2026-92",
      "at": "2026-03-02T22:21:40.760661"
    },
    {
      "processo_id": "006800.000209/2026-81",
      "at": "2026-03-02T22:22:58.324307"
    },
    {
      "processo_id": "006800.000338/2026-70",
      "at": "2026-03-02T22:24:38.694671"
    },
    {
      "processo_id": "006800.000161/2026-10",
      "at": "2026-03-02T22:25:41.809260"
    },
    {
      "processo_id": "006800.000187/2026-50",
      "at": "2026-03-02T22:26:30.177564"
    },
    {
      "processo_id": "000184.000502/2026-77",
      "at": "2026-03-02T22:27:33.717444"
    },
    {
      "processo_id": "006800.000311/2026-87",
      "at": "2026-03-02T22:28:40.990897"
    },
    {
      "processo_id": "006800.000180/2026-38",
      "at": "2026-03-02T22:29:39.872036"
    },
    {
      "processo_id": "006800.000199/2026-84",
      "at": "2026-03-02T22:30:26.445165"
    },
    {
      "processo_id": "006800.000312/2026-21",
      "at": "2026-03-02T22:31:20.496798"
    },
    {
      "processo_id": "006800.000184/2026-16",
      "at": "2026-03-02T22:32:20.197428"
    },
    {
      "processo_id": "006800.000325/2026-09",
      "at": "2026-03-02T22:33:11.350827"
    },
    {
      "processo_id": "006800.000270/2026-29",
      "at": "2026-03-02T22:34:06.952032"
    },
    {
      "processo_id": "006800.000305/2026-20",
      "at": "2026-03-02T22:34:56.023578"
    },
    {
      "processo_id": "006800.000274/2026-15",
      "at": "2026-03-02T22:36:24.614439"
    },
    {
      "processo_id": "006800.000276/2026-04",
      "at": "2026-03-02T22:39:46.945544"
    },
    {
      "processo_id": "TUR-PRO-2025/01256",
      "at": "2026-03-02T22:41:03.280759"
    },
    {
      "processo_id": "CET-PRO-2025/02888",
      "at": "2026-03-02T22:42:00.483248"
    },
    {
      "processo_id": "006800.000323/2026-10",
      "at": "2026-03-02T22:43:02.998563"
    },
    {
      "processo_id": "006800.000152/2026-11",
      "at": "2026-03-02T22:44:01.782408"
    },
    {
      "processo_id": "006800.000106/2026-11",
      "at": "2026-03-02T22:47:15.868462"
    },
    {
      "processo_id": "006800.000211/2026-51",
      "at": "2026-03-02T22:49:29.711751"
    },
    {
      "processo_id": "TUR-PRO-2025/01235",
      "at": "2026-03-02T22:53:00.661286"
    },
    {
      "processo_id": "006800.000310/2026-32",
      "at": "2026-03-02T22:54:16.693345"
    },
    {
      "processo_id": "006800.000178/2026-69",
      "at": "2026-03-02T22:55:44.956823"
    },
    {
      "processo_id": "TUR-PRO-2025/01222",
      "at": "2026-03-02T22:57:09.675457"
    },
    {
      "processo_id": "006800.000273/2026-62",
      "at": "2026-03-02T23:00:55.826854"
    },
    {
      "processo_id": "006800.000307/2026-19",
      "at": "2026-03-02T23:03:22.377991"
    },
    {
      "processo_id": "006800.000227/2026-63",
      "at": "2026-03-02T23:05:39.037080"
    },
    {
      "processo_id": "TUR-PRO-2025/01215",
      "at": "2026-03-02T23:12:08.248813"
    },
    {
      "processo_id": "TUR-PRO-2025/01219",
      "at": "2026-03-02T23:13:10.277154"
    },
    {
      "processo_id": "006800.000334/2026-91",
      "at": "2026-03-02T23:19:49.232831"
    },
    {
      "processo_id": "006800.000271/2026-73",
      "at": "2026-03-02T23:22:09.134001"
    },
    {
      "processo_id": "TUR-PRO-2025/01225",
      "at": "2026-03-02T23:34:16.463775"
    },
    {
      "processo_id": "006800.000177/2026-14",
      "at": "2026-03-02T23:36:26.968552"
    },
    {
      "processo_id": "006800.000213/2026-40",
      "at": "2026-03-02T23:39:33.779771"
    },
    {
      "processo_id": "TRA-PRO-2025/00286",
      "at": "2026-03-02T23:41:08.319726"
    },
    {
      "processo_id": "000184.000037/2026-74",
      "at": "2026-03-02T23:42:14.482793"
    },
    {
      "processo_id": "SME-PRO-2025/61739",
      "at": "2026-03-02T23:49:01.226982"
    },
    {
      "processo_id": "12/500.078/2021",
      "at": "2026-03-02T23:51:44.779864"
    },
    {
      "processo_id": "006800.000326/2026-45",
      "at": "2026-03-02T23:56:35.740303"
    },
    {
      "processo_id": "000184.000137/2026-09",
      "at": "2026-03-02T23:58:52.456896"
    },
    {
      "processo_id": "006800.000127/2026-37",
      "at": "2026-03-03T00:05:21.368582"
    },
    {
      "processo_id": "TUR-PRO-2025/01232",
      "at": "2026-03-03T00:07:20.302892"
    },
    {
      "processo_id": "TUR-PRO-2025/01218",
      "at": "2026-03-03T00:08:32.355392"
    },
    {
      "processo_id": "006800.000324/2026-56",
      "at": "2026-03-03T00:12:38.374537"
    },
    {
      "processo_id": "006800.000164/2026-45",
      "at": "2026-03-03T00:15:01.910320"
    },
    {
      "processo_id": "000184.000082/2026-29",
      "at": "2026-03-03T00:16:06.398808"
    },
    {
      "processo_id": "006800.000257/2026-70",
      "at": "2026-03-03T00:20:48.870982"
    },
    {
      "processo_id": "006800.000272/2026-18",
      "at": "2026-03-03T00:23:14.877134"
    },
    {
      "processo_id": "006800.000335/2026-36",
      "at": "2026-03-03T00:25:10.467549"
    },
    {
      "processo_id": "006300.000004/2026-37",
      "at": "2026-03-03T00:26:31.069310"
    },
    {
      "processo_id": "006800.000330/2026-11",
      "at": "2026-03-03T00:37:54.975473"
    },
    {
      "processo_id": "006800.000309/2026-16",
      "at": "2026-03-03T00:41:08.404889"
    },
    {
      "processo_id": "006800.000055/2026-28",
      "at": "2026-03-03T00:47:56.556531"
    },
    {
      "processo_id": "006800.000306/2026-74",
      "at": "2026-03-03T00:51:05.021014"
    },
    {
      "processo_id": "000700.000325/2025-61",
      "at": "2026-03-03T00:52:24.589129"
    },
    {
      "processo_id": "006800.000331/2026-58",
      "at": "2026-03-04T17:34:39.486810"
    },
    {
      "processo_id": "006800.000285/2026-97",
      "at": "2026-03-04T17:36:31.947715"
    },
    {
      "processo_id": "006800.000329/2026-89",
      "at": "2026-03-04T17:37:01.809928"
    },
    {
      "processo_id": "006800.000328/2026-34",
      "at": "2026-03-04T17:37:59.140960"
    },
    {
      "processo_id": "006800.000200/2026-71",
      "at": "2026-03-04T17:38:51.661932"
    },
    {
      "processo_id": "006800.000097/2026-69",
      "at": "2026-03-04T17:40:37.493938"
    },
    {
      "processo_id": "006800.000269/2026-02",
      "at": "2026-03-04T17:41:45.486961"
    },
    {
      "processo_id": "001200.000596/2026-00",
      "at": "2026-03-04T17:42:32.739389"
    },
    {
      "processo_id": "001200.000602/2026-11",
      "at": "2026-03-04T17:43:20.039434"
    }
  ]
}